{
  "_meta": {
    "description": "Arcturus API — Verified Source Quality Registry",
    "generated": "2026-05-10T18:56:21.697Z",
    "generator": "GitHub Actions / quality-scanner.yml",
    "note": "Scores updated automatically every 6 hours. Do not edit manually."
  },
  "mapple": {
    "score": 68,
    "label": "720p",
    "verified": true,
    "avg_response_ms": 966
  },
  "pstream": {
    "score": 82,
    "label": "1080p",
    "verified": false,
    "avg_response_ms": 0
  },
  "multiembed": {
    "score": 69,
    "label": "720p",
    "verified": true,
    "avg_response_ms": 1005
  },
  "moviesapi": {
    "score": 71,
    "label": "720p",
    "verified": true,
    "avg_response_ms": 948
  },
  "embedsu": {
    "score": 80,
    "label": "1080p",
    "verified": false,
    "avg_response_ms": 0
  },
  "hexa": {
    "score": 78,
    "label": "1080p",
    "verified": false,
    "avg_response_ms": 0
  },
  "vidlink": {
    "score": 80,
    "label": "1080p",
    "verified": true,
    "avg_response_ms": 345
  },
  "vidsrcXyz": {
    "score": 72,
    "label": "1080p",
    "verified": false,
    "avg_response_ms": 0
  },
  "vidsrcrip": {
    "score": 73,
    "label": "1080p",
    "verified": true,
    "avg_response_ms": 705
  },
  "vidsrcsu": {
    "score": 73,
    "label": "1080p",
    "verified": true,
    "avg_response_ms": 594
  },
  "vidsrcvip": {
    "score": 71,
    "label": "1080p",
    "verified": true,
    "avg_response_ms": 1220
  },
  "2embed": {
    "score": 60,
    "label": "480p",
    "verified": true,
    "avg_response_ms": 326
  },
  "123embed": {
    "score": 58,
    "label": "480p",
    "verified": false,
    "avg_response_ms": 744
  },
  "111movies": {
    "score": 53,
    "label": "480p",
    "verified": true,
    "avg_response_ms": 1136
  },
  "smashystream": {
    "score": 58,
    "label": "720p",
    "verified": false,
    "avg_response_ms": 0
  },
  "autoembed": {
    "score": 65,
    "label": "720p",
    "verified": false,
    "avg_response_ms": 0
  },
  "videasy": {
    "score": 98,
    "label": "4K",
    "verified": true,
    "avg_response_ms": 559
  },
  "vidfast": {
    "score": 98,
    "label": "4K",
    "verified": true,
    "avg_response_ms": 631
  },
  "vidify": {
    "score": 53,
    "label": "480p",
    "verified": true,
    "avg_response_ms": 802
  },
  "flicky": {
    "score": 63,
    "label": "720p",
    "verified": true,
    "avg_response_ms": 1198
  },
  "rive": {
    "score": 62,
    "label": "720p",
    "verified": false,
    "avg_response_ms": 0
  },
  "vidora": {
    "score": 60,
    "label": "720p",
    "verified": false,
    "avg_response_ms": 0
  },
  "nebula": {
    "score": 63,
    "label": "720p",
    "verified": true,
    "avg_response_ms": 559
  },
  "vidzee": {
    "score": 88,
    "label": "1080p",
    "verified": true,
    "avg_response_ms": 889
  },
  "spenflix": {
    "score": 53,
    "label": "480p",
    "verified": true,
    "avg_response_ms": 560
  },
  "vidsrccx": {
    "score": 48,
    "label": "480p",
    "verified": false,
    "avg_response_ms": 0
  },
  "uembed": {
    "score": 45,
    "label": "unknown",
    "verified": false,
    "avg_response_ms": 0
  }
}