{
  "_meta": {
    "description": "Arcturus API — Verified Source Quality Registry",
    "generated": "2026-02-25T08:06:31.094Z",
    "generator": "GitHub Actions / quality-scanner.yml",
    "note": "Scores updated automatically every 6 hours. Do not edit manually."
  },
  "mapple": {
    "score": 65,
    "label": "720p",
    "verified": true,
    "avg_response_ms": 2958
  },
  "pstream": {
    "score": 87,
    "label": "1080p",
    "verified": true,
    "avg_response_ms": 204
  },
  "multiembed": {
    "score": 68,
    "label": "720p",
    "verified": true,
    "avg_response_ms": 3319
  },
  "moviesapi": {
    "score": 73,
    "label": "720p",
    "verified": true,
    "avg_response_ms": 212
  },
  "embedsu": {
    "score": 80,
    "label": "1080p",
    "verified": false,
    "avg_response_ms": 0
  },
  "hexa": {
    "score": 78,
    "label": "1080p",
    "verified": false,
    "avg_response_ms": 0
  },
  "vidlink": {
    "score": 78,
    "label": "1080p",
    "verified": true,
    "avg_response_ms": 820
  },
  "vidsrcXyz": {
    "score": 72,
    "label": "1080p",
    "verified": true,
    "avg_response_ms": 3024
  },
  "vidsrcrip": {
    "score": 71,
    "label": "1080p",
    "verified": true,
    "avg_response_ms": 1377
  },
  "vidsrcsu": {
    "score": 71,
    "label": "1080p",
    "verified": true,
    "avg_response_ms": 1990
  },
  "vidsrcvip": {
    "score": 70,
    "label": "1080p",
    "verified": true,
    "avg_response_ms": 3282
  },
  "2embed": {
    "score": 56,
    "label": "480p",
    "verified": true,
    "avg_response_ms": 1510
  },
  "123embed": {
    "score": 56,
    "label": "480p",
    "verified": true,
    "avg_response_ms": 1909
  },
  "111movies": {
    "score": 52,
    "label": "480p",
    "verified": true,
    "avg_response_ms": 3452
  },
  "smashystream": {
    "score": 59,
    "label": "720p",
    "verified": true,
    "avg_response_ms": 1712
  },
  "autoembed": {
    "score": 65,
    "label": "720p",
    "verified": true,
    "avg_response_ms": 3360
  },
  "videasy": {
    "score": 96,
    "label": "4K",
    "verified": true,
    "avg_response_ms": 1857
  },
  "vidfast": {
    "score": 96,
    "label": "4K",
    "verified": true,
    "avg_response_ms": 1916
  },
  "vidify": {
    "score": 50,
    "label": "480p",
    "verified": false,
    "avg_response_ms": 0
  },
  "flicky": {
    "score": 62,
    "label": "720p",
    "verified": true,
    "avg_response_ms": 3509
  },
  "rive": {
    "score": 62,
    "label": "720p",
    "verified": true,
    "avg_response_ms": 2556
  },
  "vidora": {
    "score": 60,
    "label": "720p",
    "verified": true,
    "avg_response_ms": 2768
  },
  "nebula": {
    "score": 61,
    "label": "720p",
    "verified": true,
    "avg_response_ms": 2603
  },
  "vidzee": {
    "score": 85,
    "label": "1080p",
    "verified": true,
    "avg_response_ms": 2773
  },
  "spenflix": {
    "score": 50,
    "label": "480p",
    "verified": true,
    "avg_response_ms": 2640
  },
  "vidsrccx": {
    "score": 48,
    "label": "480p",
    "verified": true,
    "avg_response_ms": 2768
  },
  "uembed": {
    "score": 45,
    "label": "unknown",
    "verified": false,
    "avg_response_ms": 0
  }
}