{
  "_meta": {
    "description": "Arcturus API — Verified Source Quality Registry",
    "generated": "2026-03-20T01:49:33.042Z",
    "generator": "GitHub Actions / quality-scanner.yml",
    "note": "Scores updated automatically every 6 hours. Do not edit manually."
  },
  "mapple": {
    "score": 66,
    "label": "720p",
    "verified": true,
    "avg_response_ms": 1549
  },
  "pstream": {
    "score": 82,
    "label": "1080p",
    "verified": false,
    "avg_response_ms": 0
  },
  "multiembed": {
    "score": 69,
    "label": "720p",
    "verified": true,
    "avg_response_ms": 1790
  },
  "moviesapi": {
    "score": 69,
    "label": "720p",
    "verified": true,
    "avg_response_ms": 1709
  },
  "embedsu": {
    "score": 80,
    "label": "1080p",
    "verified": false,
    "avg_response_ms": 0
  },
  "hexa": {
    "score": 78,
    "label": "1080p",
    "verified": false,
    "avg_response_ms": 0
  },
  "vidlink": {
    "score": 78,
    "label": "1080p",
    "verified": true,
    "avg_response_ms": 609
  },
  "vidsrcXyz": {
    "score": 73,
    "label": "1080p",
    "verified": true,
    "avg_response_ms": 1871
  },
  "vidsrcrip": {
    "score": 71,
    "label": "1080p",
    "verified": true,
    "avg_response_ms": 1027
  },
  "vidsrcsu": {
    "score": 73,
    "label": "1080p",
    "verified": true,
    "avg_response_ms": 951
  },
  "vidsrcvip": {
    "score": 71,
    "label": "1080p",
    "verified": true,
    "avg_response_ms": 1745
  },
  "2embed": {
    "score": 58,
    "label": "480p",
    "verified": true,
    "avg_response_ms": 667
  },
  "123embed": {
    "score": 56,
    "label": "480p",
    "verified": true,
    "avg_response_ms": 1093
  },
  "111movies": {
    "score": 53,
    "label": "480p",
    "verified": true,
    "avg_response_ms": 1854
  },
  "smashystream": {
    "score": 59,
    "label": "720p",
    "verified": true,
    "avg_response_ms": 1212
  },
  "autoembed": {
    "score": 65,
    "label": "720p",
    "verified": false,
    "avg_response_ms": 0
  },
  "videasy": {
    "score": 98,
    "label": "4K",
    "verified": true,
    "avg_response_ms": 880
  },
  "vidfast": {
    "score": 96,
    "label": "4K",
    "verified": true,
    "avg_response_ms": 1159
  },
  "vidify": {
    "score": 51,
    "label": "480p",
    "verified": true,
    "avg_response_ms": 1527
  },
  "flicky": {
    "score": 63,
    "label": "720p",
    "verified": true,
    "avg_response_ms": 1887
  },
  "rive": {
    "score": 63,
    "label": "720p",
    "verified": true,
    "avg_response_ms": 1478
  },
  "vidora": {
    "score": 60,
    "label": "720p",
    "verified": false,
    "avg_response_ms": 0
  },
  "nebula": {
    "score": 61,
    "label": "720p",
    "verified": true,
    "avg_response_ms": 1544
  },
  "vidzee": {
    "score": 86,
    "label": "1080p",
    "verified": true,
    "avg_response_ms": 1388
  },
  "spenflix": {
    "score": 51,
    "label": "480p",
    "verified": true,
    "avg_response_ms": 1238
  },
  "vidsrccx": {
    "score": 49,
    "label": "480p",
    "verified": true,
    "avg_response_ms": 1329
  },
  "uembed": {
    "score": 45,
    "label": "unknown",
    "verified": false,
    "avg_response_ms": 0
  }
}